Metadata-Version: 1.1
Name: pydspack
Version: 0.0.2
Summary: A basic library of Data Structures for learning
Home-page: UNKNOWN
Author: Mandar Parte
Author-email: mandarparte1709@gmail.com
License: MIT
Keywords: Data Structure,Algorithms,pyds
Platform: UNKNOWN
Classifier: Development Status :: 5 - Production/Stable
Classifier: Intended Audience :: Education
Classifier: Operating System :: OS Independent
Classifier: License :: OSI Approved :: MIT License
Classifier: Programming Language :: Python :: 3
